jsql/__init__.py
tests/__init__.py
tests/test_list_param.py
tests/test_render.py
tests/test_sql.py
tests/test_sqlproxy.py
jsql-0.91.dist-info/METADATA
jsql-0.91.dist-info/WHEEL
jsql-0.91.dist-info/top_level.txt
jsql-0.91.dist-info/zip-safe
jsql-0.91.dist-info/RECORD
